xcuitest_goblin/__init__.py
xcuitest_goblin/cli.py
xcuitest_goblin/config.py
xcuitest_goblin/analyzers/__init__.py
xcuitest_goblin/analyzers/accessibility_analyzer.py
xcuitest_goblin/analyzers/base_analyzer.py
xcuitest_goblin/analyzers/screen_graph_analyzer.py
xcuitest_goblin/analyzers/test_inventory_analyzer.py
xcuitest_goblin/analyzers/test_plan_analyzer.py
xcuitest_goblin/reporters/__init__.py
xcuitest_goblin/reporters/base_reporter.py
xcuitest_goblin/reporters/html_reporter.py
xcuitest_goblin/reporters/json_reporter.py
xcuitest_goblin/reporters/markdown_reporter.py
xcuitest_goblin/utils/__init__.py
xcuitest_goblin-2.2.1.dist-info/licenses/LICENSE
xcuitest_goblin-2.2.1.dist-info/METADATA
xcuitest_goblin-2.2.1.dist-info/WHEEL
xcuitest_goblin-2.2.1.dist-info/entry_points.txt
xcuitest_goblin-2.2.1.dist-info/top_level.txt
xcuitest_goblin-2.2.1.dist-info/RECORD
