Metadata-Version: 2.4
Name: xcuitest-goblin
Version: 2.2.1
Summary: Analyze and optimize iOS XCUITest projects - find orphaned tests, inconsistent naming, overused identifiers, and more
Author: Test Goblin Contributors
License: MIT
Project-URL: Homepage, https://github.com/jmcy9999/xcuitest-goblin
Project-URL: Documentation, https://github.com/jmcy9999/xcuitest-goblin#readme
Project-URL: Repository, https://github.com/jmcy9999/xcuitest-goblin.git
Project-URL: Issues, https://github.com/jmcy9999/xcuitest-goblin/issues
Keywords: ios,xcuitest,testing,automation,analysis,xcode,test-optimization
Classifier: Development Status :: 3 - Alpha
Classifier: Intended Audience :: Developers
Classifier: License :: OSI Approved :: MIT License
Classifier: Operating System :: OS Independent
Classifier: Programming Language :: Python :: 3
Classifier: Programming Language :: Python :: 3.10
Classifier: Programming Language :: Python :: 3.11
Classifier: Programming Language :: Python :: 3.12
Classifier: Topic :: Software Development :: Testing
Classifier: Topic :: Software Development :: Quality Assurance
Requires-Python: >=3.10
License-File: LICENSE
Provides-Extra: dev
Requires-Dist: pytest>=7.4.0; extra == "dev"
Requires-Dist: pytest-cov>=4.1.0; extra == "dev"
Requires-Dist: black>=24.1.0; extra == "dev"
Requires-Dist: flake8>=7.0.0; extra == "dev"
Requires-Dist: mypy>=1.8.0; extra == "dev"
Dynamic: license-file
